{
  "checksums": [
    {
      "id": "github_archive/github.com/tfutils/tfenv/v3.0.0",
      "checksum": "463132E45A211FA3FAF85E62FDFAA9BB746343FF1954CCBAD91CAE743DF3B648",
      "algorithm": "sha256"
    },
    {
      "id": "github_release/github.com/99designs/aws-vault/v7.2.0/aws-vault-linux-amd64",
      "checksum": "B92BCFC4A78AA8C547AE5920D196943268529C5DBC9C5ACA80B797A18A5D0693",
      "algorithm": "sha256"
    },
    {
      "id": "github_release/github.com/99designs/aws-vault/v7.2.0/aws-vault-linux-arm64",
      "checksum": "176FA59B9E3981720361CD6ED87B5389741953C62BA0A6FA4F2DB401F8BEF735",
      "algorithm": "sha256"
    },
    {
      "id": "github_release/github.com/BurntSushi/ripgrep/14.1.0/ripgrep-14.1.0-aarch64-unknown-linux-gnu.tar.gz",
      "checksum": "C8C210B99844FBF16B7A36D1C963E8351BCA5FF2DD7C788F5FBA4AC18BA8C60D",
      "algorithm": "sha256"
    },
    {
      "id": "github_release/github.com/BurntSushi/ripgrep/14.1.0/ripgrep-14.1.0-x86_64-unknown-linux-musl.tar.gz",
      "checksum": "F84757B07F425FE5CF11D87DF6644691C644A5CD2348A2C670894272999D3BA7",
      "algorithm": "sha256"
    },
    {
      "id": "github_release/github.com/PaulJuliusMartinez/jless/v0.9.0/jless-v0.9.0-x86_64-unknown-linux-gnu.zip",
      "checksum": "A1E0EB63EF347ADC649989AC5C7D2DC896DF6D494622B953C86E3A248E733A93",
      "algorithm": "sha256"
    },
    {
      "id": "github_release/github.com/ajeetdsouza/zoxide/v0.9.4/zoxide-0.9.4-aarch64-unknown-linux-musl.tar.gz",
      "checksum": "65DF93B887B58F3DB83C62505F5D5E95183745E330683A1767AF064A5FA2F133",
      "algorithm": "sha256"
    },
    {
      "id": "github_release/github.com/ajeetdsouza/zoxide/v0.9.4/zoxide-0.9.4-x86_64-unknown-linux-musl.tar.gz",
      "checksum": "FBC22C115A252F9A5C73301E35ED695810D020126B126C3D0E47F0B31F2255A0",
      "algorithm": "sha256"
    },
    {
      "id": "github_release/github.com/antonmedv/fx/34.0.0/fx_linux_amd64",
      "checksum": "9AB09469C03D964B2A1041006CC4836E58214B85082D9E887E860A9159A079FA",
      "algorithm": "sha256"
    },
    {
      "id": "github_release/github.com/antonmedv/fx/34.0.0/fx_linux_arm64",
      "checksum": "4212DAB8B41AEF7C3399C5CEAEEC27C80E044E49B90CBD18662C8F363770AA76",
      "algorithm": "sha256"
    },
    {
      "id": "github_release/github.com/aquasecurity/tfsec/v1.28.6/tfsec_1.28.6_linux_amd64.tar.gz",
      "checksum": "8CBD8D64CBD1F25B38F33FA04DB602466DADE79E99C99DC9DA053B5962D34014",
      "algorithm": "sha256"
    },
    {
      "id": "github_release/github.com/aquasecurity/tfsec/v1.28.6/tfsec_1.28.6_linux_arm64.tar.gz",
      "checksum": "4BC7B0F0592BE4FA384CFF52AF5B1CDD2066BA7A06001BEA98690340851C0BCE",
      "algorithm": "sha256"
    },
    {
      "id": "github_release/github.com/bitnami-labs/sealed-secrets/v0.26.2/kubeseal-0.26.2-linux-amd64.tar.gz",
      "checksum": "9681DD97D245E2CD24AF7D2F44C962DDD3E7EB67443F9F8AB3C0633B3B0A15A7",
      "algorithm": "sha256"
    },
    {
      "id": "github_release/github.com/bitnami-labs/sealed-secrets/v0.26.2/kubeseal-0.26.2-linux-arm64.tar.gz",
      "checksum": "22845595E1C9C3C47B3A98ECD611D026AA11286F3F31415BD247399CDF0F1364",
      "algorithm": "sha256"
    },
    {
      "id": "github_release/github.com/casey/just/1.25.2/just-1.25.2-aarch64-unknown-linux-musl.tar.gz",
      "checksum": "049D624255D150F18B0F3A1257A163366B0DC22E16526214773903125145E515",
      "algorithm": "sha256"
    },
    {
      "id": "github_release/github.com/casey/just/1.25.2/just-1.25.2-x86_64-unknown-linux-musl.tar.gz",
      "checksum": "AD56BF1A804243B51EF2C2EEC4B3A8177F970CCC414CBBEE219C2E5C06F7BCC9",
      "algorithm": "sha256"
    },
    {
      "id": "github_release/github.com/charmbracelet/glow/v1.5.1/glow_Linux_arm64.tar.gz",
      "checksum": "33661A7D97925724339D4F06E633DF7DBC98E8A70320668236895BE1B4C8125F",
      "algorithm": "sha256"
    },
    {
      "id": "github_release/github.com/charmbracelet/glow/v1.5.1/glow_Linux_x86_64.tar.gz",
      "checksum": "D224BE006FC4EE361C1D1A85DBD46C269372B76C5413E2A9BFD0F7FE52C66F78",
      "algorithm": "sha256"
    },
    {
      "id": "github_release/github.com/charmbracelet/gum/v0.14.0/gum_0.14.0_Linux_arm64.tar.gz",
      "checksum": "0F419055E7C7F38BC330C67466D179441F13DC6147FA7CB53498940E0C46F22F",
      "algorithm": "sha256"
    },
    {
      "id": "github_release/github.com/charmbracelet/gum/v0.14.0/gum_0.14.0_Linux_x86_64.tar.gz",
      "checksum": "BF93C39D706FBB48883D983B3A71CD8B1617599A70204953573B66ED0C133630",
      "algorithm": "sha256"
    },
    {
      "id": "github_release/github.com/cli/cli/v2.49.1/gh_2.49.1_linux_amd64.tar.gz",
      "checksum": "CF3A432235CAA033A87523C4C03784059CBB67DE2DAFCCFE9D735561E72AD643",
      "algorithm": "sha256"
    },
    {
      "id": "github_release/github.com/cli/cli/v2.49.1/gh_2.49.1_linux_arm64.tar.gz",
      "checksum": "CDB52928D1A9E3414A1C6877380072F7B4DF9F51FD97C0265C266462F32EC29B",
      "algorithm": "sha256"
    },
    {
      "id": "github_release/github.com/cue-lang/cue/v0.8.2/cue_v0.8.2_linux_amd64.tar.gz",
      "checksum": "9C95DF381722B8E547AB6F257981C73246AC7C7F7A6DA7571B405BEF6FFB22A0",
      "algorithm": "sha256"
    },
    {
      "id": "github_release/github.com/cue-lang/cue/v0.8.2/cue_v0.8.2_linux_arm64.tar.gz",
      "checksum": "AF846C9C11925F4F28F051B8778C779535A307923D7D5FB2A9BDC92AA5925325",
      "algorithm": "sha256"
    },
    {
      "id": "github_release/github.com/dagger/dagger/v0.11.2/dagger_v0.11.2_linux_amd64.tar.gz",
      "checksum": "2A3C1B8669FC7995D7F4514C156557A03509A4A5C85D321AFAEB7AABAF0E20AE",
      "algorithm": "sha256"
    },
    {
      "id": "github_release/github.com/dagger/dagger/v0.11.2/dagger_v0.11.2_linux_arm64.tar.gz",
      "checksum": "52B1CCBBA4CAEC8A9450C1BB4A04AFFDA9D927F24459B71F1937DD8D8BA01C00",
      "algorithm": "sha256"
    },
    {
      "id": "github_release/github.com/dandavison/delta/0.17.0/delta-0.17.0-aarch64-unknown-linux-gnu.tar.gz",
      "checksum": "8318BB267AB3A01F4E7B9480C4C3B2A5895C0287ABFC5586306F5A2F2825882B",
      "algorithm": "sha256"
    },
    {
      "id": "github_release/github.com/dandavison/delta/0.17.0/delta-0.17.0-x86_64-unknown-linux-musl.tar.gz",
      "checksum": "0CB2C2E196A78C84E47C303119AD561D3D4DEBFC8CC93D3AB5AE866FB7EFD126",
      "algorithm": "sha256"
    },
    {
      "id": "github_release/github.com/denisidoro/navi/v2.23.0/navi-v2.23.0-aarch64-unknown-linux-gnu.tar.gz",
      "checksum": "5CB511718B8DB1767DFF4E22EB02D2F296E91EBF4205AFF3CC84996BFD476C30",
      "algorithm": "sha256"
    },
    {
      "id": "github_release/github.com/denisidoro/navi/v2.23.0/navi-v2.23.0-x86_64-unknown-linux-musl.tar.gz",
      "checksum": "1C3023825E72008052F84F5FAB842820567DFAED095F713EE01AE91839022385",
      "algorithm": "sha256"
    },
    {
      "id": "github_release/github.com/derailed/k9s/v0.32.4/k9s_Linux_amd64.tar.gz",
      "checksum": "D62611D9BE2C35B782A765E98421500196ACBF8BE844CD3D9E32D4FA7846DA05",
      "algorithm": "sha256"
    },
    {
      "id": "github_release/github.com/derailed/k9s/v0.32.4/k9s_Linux_arm64.tar.gz",
      "checksum": "ADFBE3DE1FFD3F119FF27D76D9A493E08ADB2536F9B79D08FA245DDB75A5FE52",
      "algorithm": "sha256"
    },
    {
      "id": "github_release/github.com/direnv/direnv/v2.34.0/direnv.linux-amd64",
      "checksum": "F7F2C814C2EAE48641E4BDE9BF11F463E309C8F7E3737F96C78588150E1DCE25",
      "algorithm": "sha256"
    },
    {
      "id": "github_release/github.com/direnv/direnv/v2.34.0/direnv.linux-arm64",
      "checksum": "AB34F12471841A048A343190426B434547BF2B9D258B1C8303DBDACA0D0A34AA",
      "algorithm": "sha256"
    },
    {
      "id": "github_release/github.com/dkaslovsky/nav/v1.1.0/nav_linux_amd64",
      "checksum": "0BF077F56300446CBC6A9FE265D3ECA3336B14C342E101524CACA0B0ECE55AD6",
      "algorithm": "sha256"
    },
    {
      "id": "github_release/github.com/dkaslovsky/nav/v1.1.0/nav_linux_arm64",
      "checksum": "F200511AF67401242D2D70707DD7691926C6CD5284350DA0C8106C14B7ED65AE",
      "algorithm": "sha256"
    },
    {
      "id": "github_release/github.com/dprint/dprint/0.45.1/dprint-x86_64-unknown-linux-gnu.zip",
      "checksum": "4E0C1D4F0F9F41EFC08D929616C9F73ABEA7E57B9658A8F5F478A26E165C331C",
      "algorithm": "sha256"
    },
    {
      "id": "github_release/github.com/dwisiswant0/tlder/v0.1.0/tlder_v0.1.0-linux_arm64",
      "checksum": "C55446E2E28C339D80354B23DF02E95ED41BC48C254AA5A47D8EA45212E5A9E9",
      "algorithm": "sha256"
    },
    {
      "id": "github_release/github.com/dwisiswant0/tlder/v0.1.0/tlder_v0.1.0-linux_x86_64",
      "checksum": "6FF7F28B795909984825CB8AA12CC77612989327DB84AA9A27DB917246E2FE6E",
      "algorithm": "sha256"
    },
    {
      "id": "github_release/github.com/eksctl-io/eksctl/v0.176.0/eksctl_Linux_amd64.tar.gz",
      "checksum": "912FC428EF71342476B182B849F76FA9060DFECC64C6CBA5DB03A605180968EE",
      "algorithm": "sha256"
    },
    {
      "id": "github_release/github.com/eksctl-io/eksctl/v0.176.0/eksctl_Linux_arm64.tar.gz",
      "checksum": "BD65DF007588A547DDFE06E209F1EDFC4548001286389A3EB9146AE2C7B3F6EA",
      "algorithm": "sha256"
    },
    {
      "id": "github_release/github.com/eza-community/eza/v0.18.15/eza_aarch64-unknown-linux-gnu.tar.gz",
      "checksum": "C71F43D1208EDEC028C381E3DCA46890DC7EB6BA588DEB7A5EA43DD6D2A85F9A",
      "algorithm": "sha256"
    },
    {
      "id": "github_release/github.com/eza-community/eza/v0.18.15/eza_x86_64-unknown-linux-musl.tar.gz",
      "checksum": "5F50CE6C280DE988FD05AB7E3768F37A678D9CCBE65F48A3A3482B08227C875C",
      "algorithm": "sha256"
    },
    {
      "id": "github_release/github.com/fluxcd/flux2/v2.2.3/flux_2.2.3_linux_amd64.tar.gz",
      "checksum": "9A705DF552DF5AC638F93D7FC43D9D8CDA6A78F01A16736AE6F355F4A84EBDB3",
      "algorithm": "sha256"
    },
    {
      "id": "github_release/github.com/fluxcd/flux2/v2.2.3/flux_2.2.3_linux_arm64.tar.gz",
      "checksum": "A8DCF688296AEDEC3225FB2C183C9E2CE3BDA26788D10F9D01DDB7BDB5B55288",
      "algorithm": "sha256"
    },
    {
      "id": "github_release/github.com/gokcehan/lf/r28/lf-linux-amd64.tar.gz",
      "checksum": "4EF583838437FE1F4A3DCEC78C96679C6B79E2E5405432EFE9BAA7EE341746C5",
      "algorithm": "sha256"
    },
    {
      "id": "github_release/github.com/gokcehan/lf/r28/lf-linux-arm64.tar.gz",
      "checksum": "CECA4B5B91C57E484AC716150DCEC5F83149248CCACE451D73027C883349679B",
      "algorithm": "sha256"
    },
    {
      "id": "github_release/github.com/golangci/golangci-lint/v1.58.1/golangci-lint-1.58.1-linux-amd64.tar.gz",
      "checksum": "2E7C1B2AF70ECB7CE18DA79A3951DB7046DCB709566C018FB93C61E8733B2239",
      "algorithm": "sha256"
    },
    {
      "id": "github_release/github.com/golangci/golangci-lint/v1.58.1/golangci-lint-1.58.1-linux-arm64.tar.gz",
      "checksum": "E78F55156EF7F8BD4A746AA695C6BD299DC0AA71B91EC066680D2C59E443708B",
      "algorithm": "sha256"
    },
    {
      "id": "github_release/github.com/gruntwork-io/terragrunt/v0.58.3/terragrunt_linux_amd64",
      "checksum": "366CE8D073D5F19B0E86E29883CAF9859A06F189C2334A46C2132C65155744E9",
      "algorithm": "sha256"
    },
    {
      "id": "github_release/github.com/gruntwork-io/terragrunt/v0.58.3/terragrunt_linux_arm64",
      "checksum": "1702CCB6B56C6EA6ADB2D29A7A1FA105FC0B315EE427E5A35F6BD7AF59DF9C14",
      "algorithm": "sha256"
    },
    {
      "id": "github_release/github.com/hadolint/hadolint/v2.12.0/hadolint-Linux-arm64",
      "checksum": "5798551BF19F33951881F15EB238F90AEF023F11E7EC7E9F4C37961CB87C5DF6",
      "algorithm": "sha256"
    },
    {
      "id": "github_release/github.com/hadolint/hadolint/v2.12.0/hadolint-Linux-x86_64",
      "checksum": "56DE6D5E5EC427E17B74FA48D51271C7FC0D61244BF5C90E828AAB8362D55010",
      "algorithm": "sha256"
    },
    {
      "id": "github_release/github.com/homeport/dyff/v1.7.1/dyff_1.7.1_linux_amd64.tar.gz",
      "checksum": "EBF8627F989E574865EF3F5091343DED89E151358D4698EDFD1F853EF70C6422",
      "algorithm": "sha256"
    },
    {
      "id": "github_release/github.com/homeport/dyff/v1.7.1/dyff_1.7.1_linux_arm64.tar.gz",
      "checksum": "58960AD73DB78AF3BD46FFE219C40271EC040C5156D8F890A823DB75561313E5",
      "algorithm": "sha256"
    },
    {
      "id": "github_release/github.com/instrumenta/kubeval/v0.16.1/kubeval-linux-amd64.tar.gz",
      "checksum": "2D6F9BDA1423B93787FA05D9E8DFCE2FC1190FEFBCD9D0936B9635F3F78BA790",
      "algorithm": "sha256"
    },
    {
      "id": "github_release/github.com/int128/ghcp/v1.13.2/ghcp_linux_amd64.zip",
      "checksum": "6B9D9C9A7B834237B6579353477DF3BB3730C11788170AD2A9E5D1230ABC6216",
      "algorithm": "sha256"
    },
    {
      "id": "github_release/github.com/itchyny/json2yaml/v0.1.4/json2yaml_v0.1.4_linux_amd64.tar.gz",
      "checksum": "5305F6F4A03891359C1DA224402844A1CCBA57376DABA94E0195D47FFD5DF546",
      "algorithm": "sha256"
    },
    {
      "id": "github_release/github.com/itchyny/json2yaml/v0.1.4/json2yaml_v0.1.4_linux_arm64.tar.gz",
      "checksum": "C9288F3A1C58E6B6222306E717F1B8E0CE8AF036A4CEB2EF38CFB025ED113E64",
      "algorithm": "sha256"
    },
    {
      "id": "github_release/github.com/jesseduffield/lazygit/v0.41.0/lazygit_0.41.0_Linux_arm64.tar.gz",
      "checksum": "E28A4AA146927B3307B32C3ABBDF719B1DFD7FDD08783D1D2BC7E52980CCF0C3",
      "algorithm": "sha256"
    },
    {
      "id": "github_release/github.com/jesseduffield/lazygit/v0.41.0/lazygit_0.41.0_Linux_x86_64.tar.gz",
      "checksum": "697A11091362D591E202EC01C76BACF3AF692AABEB9656A6BF9B6FF4792259D4",
      "algorithm": "sha256"
    },
    {
      "id": "github_release/github.com/jqlang/jq/jq-1.6/jq-linux64",
      "checksum": "AF986793A515D500AB2D35F8D2AECD656E764504B789B66D7E1A0B727A124C44",
      "algorithm": "sha256"
    },
    {
      "id": "github_release/github.com/jtyr/gbt/v2.0.0/gbt-2.0.0-linux-amd64.tar.gz",
      "checksum": "BE4ECFBFFD6743C9C49B505A4B41D270F9779FB3035B38E44BCA754C4000CF5D",
      "algorithm": "sha256"
    },
    {
      "id": "github_release/github.com/jtyr/gbt/v2.0.0/gbt-2.0.0-linux-arm64.tar.gz",
      "checksum": "891FD4A0192FB7F87CC149F0DFD494FD2C16DCF4FEABB87847639DDF03C89265",
      "algorithm": "sha256"
    },
    {
      "id": "github_release/github.com/junegunn/fzf/0.52.0/fzf-0.52.0-linux_amd64.tar.gz",
      "checksum": "791510A7436713F87034429585E6C19B7ECF5BB1B76089C946E18575AA5FD11F",
      "algorithm": "sha256"
    },
    {
      "id": "github_release/github.com/junegunn/fzf/0.52.0/fzf-0.52.0-linux_arm64.tar.gz",
      "checksum": "55FAA87DED40CC9C57327CB50D5345DEBEBF77679BB23650A71380EC82D50184",
      "algorithm": "sha256"
    },
    {
      "id": "github_release/github.com/kevincobain2000/gobrew/v1.10.8/gobrew-linux-amd64",
      "checksum": "CE08218D547953F36D31A5DEF3E39CC2BCCD1D5EE4A81EF3583DBD69C70096F5",
      "algorithm": "sha256"
    },
    {
      "id": "github_release/github.com/kevincobain2000/gobrew/v1.10.8/gobrew-linux-arm64",
      "checksum": "AF485E8C48A99260DC71998DF3F7A6D887204C852DB025480948E4FBADB4448C",
      "algorithm": "sha256"
    },
    {
      "id": "github_release/github.com/koalaman/shellcheck/v0.10.0/shellcheck-v0.10.0.linux.aarch64.tar.xz",
      "checksum": "324A7E89DE8FA2AED0D0C28F3DAB59CF84C6D74264022C00C22AF665ED1A09BB",
      "algorithm": "sha256"
    },
    {
      "id": "github_release/github.com/koalaman/shellcheck/v0.10.0/shellcheck-v0.10.0.linux.x86_64.tar.xz",
      "checksum": "6C881AB0698E4E6EA235245F22832860544F17BA386442FE7E9D629F8CBEDF87",
      "algorithm": "sha256"
    },
    {
      "id": "github_release/github.com/konradsz/igrep/v1.2.0/igrep-v1.2.0-x86_64-unknown-linux-gnu.tar.gz",
      "checksum": "0D412250678160E340F9CB49DE9228A71606383B943A7CE0150B21900B1654C9",
      "algorithm": "sha256"
    },
    {
      "id": "github_release/github.com/kubernetes-sigs/krew/v0.4.4/krew-linux_amd64.tar.gz",
      "checksum": "E471396B0ED4F2BE092B4854CC030DFCBB12B86197972E7BEF0CB89AD9C72477",
      "algorithm": "sha256"
    },
    {
      "id": "github_release/github.com/kubernetes-sigs/krew/v0.4.4/krew-linux_arm64.tar.gz",
      "checksum": "F8F0CDBF698ED3E8CB46E7BD213754701341A10E11CCB69C90D4863E0CF5A16A",
      "algorithm": "sha256"
    },
    {
      "id": "github_release/github.com/kubernetes-sigs/kustomize/kustomize/v5.4.1/kustomize_v5.4.1_linux_amd64.tar.gz",
      "checksum": "3D659A80398658D4FEC4EC4CA184B432AFA1D86451A60BE63CA6E14311FC1C42",
      "algorithm": "sha256"
    },
    {
      "id": "github_release/github.com/kubernetes-sigs/kustomize/kustomize/v5.4.1/kustomize_v5.4.1_linux_arm64.tar.gz",
      "checksum": "123B9CE38E04A03DE5907153EF7F16979027BAD16D0763A304E59DCF69AC6D30",
      "algorithm": "sha256"
    },
    {
      "id": "github_release/github.com/lsd-rs/lsd/v1.1.2/lsd-v1.1.2-aarch64-unknown-linux-musl.tar.gz",
      "checksum": "BC749DBA0807651AF816F6C7C30545A731F1721EB276DAABDF78DF4B0D8ED12B",
      "algorithm": "sha256"
    },
    {
      "id": "github_release/github.com/lsd-rs/lsd/v1.1.2/lsd-v1.1.2-x86_64-unknown-linux-musl.tar.gz",
      "checksum": "E6A5F424BC2E377B372BAD0CCD3FA3CE42DEE5BFEE9546AE07F0618D500DC94C",
      "algorithm": "sha256"
    },
    {
      "id": "github_release/github.com/magefile/mage/v1.15.0/mage_1.15.0_Linux-64bit.tar.gz",
      "checksum": "AF8FB0C72944EC6E31C5DD54E642083400157883602F4A89A692C4BA96EE1E66",
      "algorithm": "sha256"
    },
    {
      "id": "github_release/github.com/magefile/mage/v1.15.0/mage_1.15.0_Linux-ARM64.tar.gz",
      "checksum": "914E3866931B0B13B8D4C569C6D29BE93BB6BA976B0F7797E3DAF1D6D9F55EB3",
      "algorithm": "sha256"
    },
    {
      "id": "github_release/github.com/marcosnils/bin/v0.17.5/bin_0.17.5_linux_amd64",
      "checksum": "15D93D0A9C053A7D1D0EDCEE12DD7C2B4B2BF594B2358B0BD1C5AEE401C0C159",
      "algorithm": "sha256"
    },
    {
      "id": "github_release/github.com/marcosnils/bin/v0.17.5/bin_0.17.5_linux_arm64",
      "checksum": "FA312065E161B66AF481F3B6EDE162073EE1814DD866E939BECED73CAE088D65",
      "algorithm": "sha256"
    },
    {
      "id": "github_release/github.com/mikefarah/yq/v4.43.1/yq_linux_amd64",
      "checksum": "CFBBB9BA72C9402EF4AB9D8F843439693DFB380927921740E51706D90869C7E1",
      "algorithm": "sha256"
    },
    {
      "id": "github_release/github.com/mikefarah/yq/v4.43.1/yq_linux_arm64",
      "checksum": "A8186EFB079673293289F8C31EE252B0D533C7BB8B1ADA6A778DDD5EC0F325B6",
      "algorithm": "sha256"
    },
    {
      "id": "github_release/github.com/muesli/duf/v0.8.1/duf_0.8.1_linux_arm64.tar.gz",
      "checksum": "66D304427BB30E5766E66E740394B0B07BD852B64CC5CDA755EAB33ADF853E72",
      "algorithm": "sha256"
    },
    {
      "id": "github_release/github.com/muesli/duf/v0.8.1/duf_0.8.1_linux_x86_64.tar.gz",
      "checksum": "A8343EED730DF04ACFC0BA1553B99B4EF91D5122CAB58EE241EA8196948408D7",
      "algorithm": "sha256"
    },
    {
      "id": "github_release/github.com/mvdan/sh/v3.8.0/shfmt_v3.8.0_linux_amd64",
      "checksum": "27B3C6F9D9592FC5B4856C341D1FF2C88856709B9E76469313642A1D7B558FE0",
      "algorithm": "sha256"
    },
    {
      "id": "github_release/github.com/mvdan/sh/v3.8.0/shfmt_v3.8.0_linux_arm64",
      "checksum": "27E1F69B0D57C584BCBF5C882B4C4F78FFCF945D0EFEF45C1FBFC6692213C7C3",
      "algorithm": "sha256"
    },
    {
      "id": "github_release/github.com/nektos/act/v0.2.62/act_Linux_arm64.tar.gz",
      "checksum": "FC21CE0C8CD7400B1675C7F952A1E0C47B1DE12CE311E473215E28C70B5476A4",
      "algorithm": "sha256"
    },
    {
      "id": "github_release/github.com/nektos/act/v0.2.62/act_Linux_x86_64.tar.gz",
      "checksum": "0C0CE8066B320A07D7BC1F52F089CC1B09D4EB6BF524F823C1DCA4348DEB78CE",
      "algorithm": "sha256"
    },
    {
      "id": "github_release/github.com/neovim/neovim/stable/nvim-linux64.tar.gz",
      "checksum": "44EE395D9B5F8A14BE8EC00D3B8EAD34E18FE6461E40C9C8C50E6956D643B6CA",
      "algorithm": "sha256"
    },
    {
      "id": "github_release/github.com/rhysd/hgrep/v0.3.7/hgrep-v0.3.7-aarch64-unknown-linux-gnu.zip",
      "checksum": "3F3D48505C73497FC3F796EA5E8A1B9D57F676AA93803DC05341F9F1A45C549B",
      "algorithm": "sha256"
    },
    {
      "id": "github_release/github.com/rhysd/hgrep/v0.3.7/hgrep-v0.3.7-x86_64-unknown-linux-musl.zip",
      "checksum": "9408271895E3C74C788A9BF4806F53BBFBD4D98CFA11AEB24F7AC41409A310B5",
      "algorithm": "sha256"
    },
    {
      "id": "github_release/github.com/sharkdp/bat/v0.24.0/bat-v0.24.0-aarch64-unknown-linux-gnu.tar.gz",
      "checksum": "FECCAE9A0576D97609C57E32D3914C5116136EAB0DF74C2AB74EF397D42C5B10",
      "algorithm": "sha256"
    },
    {
      "id": "github_release/github.com/sharkdp/bat/v0.24.0/bat-v0.24.0-x86_64-unknown-linux-musl.tar.gz",
      "checksum": "D39A21E3DA57FE6A3E07184B3C1DC245F8DBA379AF569D3668B6DCDFE75E3052",
      "algorithm": "sha256"
    },
    {
      "id": "github_release/github.com/sharkdp/fd/v9.0.0/fd-v9.0.0-aarch64-unknown-linux-gnu.tar.gz",
      "checksum": "94844B8BDB8E7D48D4AA48574A6BA8BC404A88B1043E5B857602B91F6DFB188A",
      "algorithm": "sha256"
    },
    {
      "id": "github_release/github.com/sharkdp/fd/v9.0.0/fd-v9.0.0-x86_64-unknown-linux-musl.tar.gz",
      "checksum": "069E2D58127DDD944C03A2684AD79F72E3F9BD3E0D2642C36ADC5B367C134592",
      "algorithm": "sha256"
    },
    {
      "id": "github_release/github.com/sigstore/cosign/v2.2.4/cosign-linux-amd64",
      "checksum": "97A6A1E15668A75FC4FF7A4DC4CB2F098F929CBEA2F12FAA9DE31DB6B42B17D7",
      "algorithm": "sha256"
    },
    {
      "id": "github_release/github.com/sigstore/cosign/v2.2.4/cosign-linux-arm64",
      "checksum": "658087351E1D4F9C396B5F59EE5437461C06128F4CE80BA899CCAA1C0B6A8A62",
      "algorithm": "sha256"
    },
    {
      "id": "github_release/github.com/simulot/immich-go/0.13.2/immich-go_Linux_arm64.tar.gz",
      "checksum": "3BCCF01332BA35F0B28DF07CBB6981BACB97AF052569AC5C4519855371C1950E",
      "algorithm": "sha256"
    },
    {
      "id": "github_release/github.com/simulot/immich-go/0.13.2/immich-go_Linux_x86_64.tar.gz",
      "checksum": "DF654A25FE44A7BBF73AF979A7DDB1ABAF6BD8578D4C0EE4EC85A8F895A68D13",
      "algorithm": "sha256"
    },
    {
      "id": "github_release/github.com/smallstep/certificates/v0.26.1/step-ca_linux_0.26.1_amd64.tar.gz",
      "checksum": "8E398884F7C7B60EDBDFB00183BE794B404A021051268D34931EB60BB5F576D0",
      "algorithm": "sha256"
    },
    {
      "id": "github_release/github.com/smallstep/certificates/v0.26.1/step-ca_linux_0.26.1_arm64.tar.gz",
      "checksum": "B110EA07DCE74705619834FCAE8D28CF7B84CF83DA48CE4D82E231868BCB3C7C",
      "algorithm": "sha256"
    },
    {
      "id": "github_release/github.com/smallstep/cli/v0.26.1/step_linux_0.26.1_amd64.tar.gz",
      "checksum": "CE40DC908F9540C076615C6412FFE2E7C2FEA100F88B2FCC2AD2E4D8384EFCE4",
      "algorithm": "sha256"
    },
    {
      "id": "github_release/github.com/smallstep/cli/v0.26.1/step_linux_0.26.1_arm64.tar.gz",
      "checksum": "24C8AEB16CF25D47C52DB6596D081688903B01BB5857D455AABEF42CED408690",
      "algorithm": "sha256"
    },
    {
      "id": "github_release/github.com/snyk/cli/v1.1291.0/snyk-linux",
      "checksum": "8F0469B01EF00D0FAD6CE6F16D6E3E502311B1BFA5BD2B058F5EC5A83E6668CD",
      "algorithm": "sha256"
    },
    {
      "id": "github_release/github.com/snyk/cli/v1.1291.0/snyk-linux-arm64",
      "checksum": "D9A237CE55904A74D4D7E752D99689C9799ECB673B20D5988A96F62BBFAC7FF5",
      "algorithm": "sha256"
    },
    {
      "id": "github_release/github.com/starship/starship/v1.18.2/starship-aarch64-unknown-linux-musl.tar.gz",
      "checksum": "6599B4653AEF7D5B1D3BD60A2940EB5084D0B2D66D69D5D4B9EF3802CB15E14F",
      "algorithm": "sha256"
    },
    {
      "id": "github_release/github.com/starship/starship/v1.18.2/starship-x86_64-unknown-linux-musl.tar.gz",
      "checksum": "F2665EEA49C900DF7CA1A5E91FD5A530A3D607282287B1392974843588E75B5C",
      "algorithm": "sha256"
    },
    {
      "id": "github_release/github.com/stern/stern/v1.29.0/stern_1.29.0_linux_amd64.tar.gz",
      "checksum": "36D62137F7FE3B6579AD0590B4B5E6EBE1F0EDCC2432CA7C40D9D28AAB17B0A7",
      "algorithm": "sha256"
    },
    {
      "id": "github_release/github.com/stern/stern/v1.29.0/stern_1.29.0_linux_arm64.tar.gz",
      "checksum": "89612B7028B907F1507C246A2CD80F46F37627455C25721836138DDD26D59873",
      "algorithm": "sha256"
    },
    {
      "id": "github_release/github.com/suzuki-shunsuke/yaml2json/v0.2.1/yaml2json_linux_amd64.tar.gz",
      "checksum": "123F28A73C03F002F51EE8EE870076B6941D153DE4377A2759B48A770B813908",
      "algorithm": "sha256"
    },
    {
      "id": "github_release/github.com/suzuki-shunsuke/yaml2json/v0.2.1/yaml2json_linux_arm64.tar.gz",
      "checksum": "EDB318F2D836ED8F73BADA0DDFFBE4F73886731FC3BD84F8AEBF59A1C9334769",
      "algorithm": "sha256"
    },
    {
      "id": "github_release/github.com/terraform-linters/tflint/v0.51.0/tflint_linux_amd64.zip",
      "checksum": "F823712C2C8D020744363AF33307FBDE7B03169902C71D9E64CE113E61526B7E",
      "algorithm": "sha256"
    },
    {
      "id": "github_release/github.com/terraform-linters/tflint/v0.51.0/tflint_linux_arm64.zip",
      "checksum": "E2C7C2E999E969171791478DAB2835E7F2AAFDA6BBEED13F9E2835579D2017D8",
      "algorithm": "sha256"
    },
    {
      "id": "github_release/github.com/tomnomnom/gron/v0.7.1/gron-linux-amd64-0.7.1.tgz",
      "checksum": "CA0335826B02B044FA05D7E951521E45C6CED1C381A73ED5803450088E18BF22",
      "algorithm": "sha256"
    },
    {
      "id": "github_release/github.com/tomnomnom/gron/v0.7.1/gron-linux-arm64-0.7.1.tgz",
      "checksum": "5D1D4764723A0F768D9DDEF0685A052F564C8BBF5E475382342FAF4224A07D80",
      "algorithm": "sha256"
    },
    {
      "id": "github_release/github.com/twpayne/chezmoi/v2.48.0/chezmoi_2.48.0_linux_amd64.tar.gz",
      "checksum": "23CAC11DEC6D944378A3D993BA3EF26CF91BA5CD8DE8063B9EC19D207C22D300",
      "algorithm": "sha256"
    },
    {
      "id": "github_release/github.com/twpayne/chezmoi/v2.48.0/chezmoi_2.48.0_linux_arm64.tar.gz",
      "checksum": "CBAD2F57726BE6C897FE835F28F1E8370AB0DA4CECFEDCAEA24A844B36066012",
      "algorithm": "sha256"
    },
    {
      "id": "github_release/github.com/wagoodman/dive/v0.12.0/dive_0.12.0_linux_amd64.tar.gz",
      "checksum": "20A7966523A0905F950C4FBF26471734420D6788CFFFCD4A8C4BC972FDED3E96",
      "algorithm": "sha256"
    },
    {
      "id": "github_release/github.com/zellij-org/zellij/v0.40.1/zellij-aarch64-unknown-linux-musl.tar.gz",
      "checksum": "0DF0D66B4990310828C87097F0A89819184AEE1F09BA51F4EC5963FAE51FCD31",
      "algorithm": "sha256"
    },
    {
      "id": "github_release/github.com/zellij-org/zellij/v0.40.1/zellij-x86_64-unknown-linux-musl.tar.gz",
      "checksum": "A9FD3EF2D9BB2FD829E0CE024E9B0D718B8B5140DE6194484CC1110ED324370F",
      "algorithm": "sha256"
    },
    {
      "id": "http/amazon-ecr-credential-helper-releases.s3.us-east-2.amazonaws.com/0.7.1/linux-amd64/docker-credential-ecr-login",
      "checksum": "A82CC3ED2CF959616212E3C3C3893DDA4F7886DA1447C444EF541E6F595AE087",
      "algorithm": "sha256"
    },
    {
      "id": "http/dl.k8s.io/v1.30.0/bin/linux/amd64/kubectl",
      "checksum": "7C3807C0F5C1B30110A2FF1E55DA1D112A6D0096201F1BEB81B269F582B5D1C5",
      "algorithm": "sha256"
    },
    {
      "id": "http/dl.k8s.io/v1.30.0/bin/linux/arm64/kubectl",
      "checksum": "669AF0CF520757298EA60A8B6EB6B719BA443A9C7D35F36D3FB2FD7513E8C7D2",
      "algorithm": "sha256"
    },
    {
      "id": "http/get.helm.sh/helm-v3.14.4-linux-amd64.tar.gz",
      "checksum": "A5844EF2C38EF6DDF3B5A8F7D91E7E0E8EBC39A38BB3FC8013D629C1EF29C259",
      "algorithm": "sha256"
    },
    {
      "id": "http/get.helm.sh/helm-v3.14.4-linux-arm64.tar.gz",
      "checksum": "113CCC53B7C57C2ABA0CD0AA560B5500841B18B5210D78641ACFDDC53DAC8AB2",
      "algorithm": "sha256"
    },
    {
      "id": "http/releases.hashicorp.com/packer/1.10.3/packer_1.10.3_linux_amd64.zip",
      "checksum": "12977FDE5F4FBBB0A88B4E8DC59C2F899113E57292D02A8BDC0EFECF8CB3A9A2",
      "algorithm": "sha256"
    },
    {
      "id": "http/releases.hashicorp.com/packer/1.10.3/packer_1.10.3_linux_arm64.zip",
      "checksum": "5803DC279FC1F1AB98020B9BCB08E9702DAB96EDA10A5D09C3FBE849F9AFB498",
      "algorithm": "sha256"
    },
    {
      "id": "http/storage.googleapis.com/minikube/releases/v1.33.0/minikube-linux-amd64",
      "checksum": "4BFDC17F0DCE678432D5C02C2A681C7A72921CB72AA93CCC00C112070EC5D2BC",
      "algorithm": "sha256"
    },
    {
      "id": "http/storage.googleapis.com/minikube/releases/v1.33.0/minikube-linux-arm64",
      "checksum": "D7AFB43F87190331B2AEE451EEF0BAE699C93D0ACB7B57404CC6B6D3698033A7",
      "algorithm": "sha256"
    },
    {
      "id": "http/storage.googleapis.com/skaffold/releases/v2.11.1/skaffold-linux-amd64",
      "checksum": "5DB2B008F1CA44E1C82B98EBA400125FE24544D1B9A07458DCBD3E1B7BAE2633",
      "algorithm": "sha256"
    },
    {
      "id": "http/storage.googleapis.com/skaffold/releases/v2.11.1/skaffold-linux-arm64",
      "checksum": "7CCB4F73EE6B9E3ADA7E77F1049BA621E423E9D924CB2B614FF3C45188F8918E",
      "algorithm": "sha256"
    },
    {
      "id": "http/trunk.io/releases/launcher/1.3.1/trunk",
      "checksum": "92251C73B4453E8ED45B311ED9A4369EB6C8DC667FCDFC4E94E756C3B605A00B",
      "algorithm": "sha256"
    },
    {
      "id": "registries/github_content/github.com/aquaproj/aqua-registry/v4.174.0/registry.yaml",
      "checksum": "87915F6D4E44FFE6C0B6ED9F71625CEEAB45B85C6C3596579A768CABEAB70E55741121C5C225E3AD7174F328195D90952CA67572DF012CED300BFC7C9EAFBC5A",
      "algorithm": "sha512"
    }
  ]
}
